kel/__init__.py
kel/__main__.py
kel/__version__.py
kel/assistant/__init__.py
kel/assistant/assist_test.py
kel/assistant/summon_assistant.py
kel/config/__init__.py
kel/config/get_configs.py
kel/constants/__init__.py
kel/constants/base_price.py
kel/constants/constants.py
kel/gpt/__init__.py
kel/gpt/askanthropic.py
kel/gpt/askgoogle.py
kel/gpt/askgpt.py
kel/gpt/askollama.py
kel/gpt/askopenai.py
kel/inputs/__init__.py
kel/inputs/gatekeeper.py
kel/inputs/inputs.py
kel/utils/__init__.py
kel/utils/cost.py
kel/utils/models.py
kel/utils/utils.py
kel_cli-0.0.13.dist-info/LICENSE
kel_cli-0.0.13.dist-info/METADATA
kel_cli-0.0.13.dist-info/WHEEL
kel_cli-0.0.13.dist-info/entry_points.txt
kel_cli-0.0.13.dist-info/RECORD
