Metadata-Version: 2.1
Name: kel-cli
Version: 0.0.13
Summary: AI assistant in your CLI.
License: MIT
Keywords: gpt,cli,llm,openai,anthropic,kel,google,ollama,ai,artificial intelligence,assistant,chatbot,chat
Author: NaveenKumar Namachivayam
Author-email: catch.nkn@gmail.com
Requires-Python: >=3.10,<4.0
Classifier: License :: OSI Approved :: MIT License
Classifier: Programming Language :: Python :: 3
Classifier: Programming Language :: Python :: 3.10
Classifier: Programming Language :: Python :: 3.11
Classifier: Programming Language :: Python :: 3.12
Requires-Dist: annotated-types (>=0.6.0,<0.7.0)
Requires-Dist: anthropic (>=0.7.8,<0.8.0)
Requires-Dist: anyio (>=4.1.0,<5.0.0)
Requires-Dist: certifi (>=2023.11.17,<2024.0.0)
Requires-Dist: click (>=8.1.7,<9.0.0)
Requires-Dist: colorama (>=0.4.6,<0.5.0)
Requires-Dist: distro (>=1.8.0,<2.0.0)
Requires-Dist: exceptiongroup (>=1.2.0,<2.0.0)
Requires-Dist: google-generativeai (>=0.3.1,<0.4.0)
Requires-Dist: h11 (>=0.14.0,<0.15.0)
Requires-Dist: httpcore (>=1.0.2,<2.0.0)
Requires-Dist: httpx (>=0.25.2,<0.26.0)
Requires-Dist: idna (>=3.6,<4.0)
Requires-Dist: langchain (>=0.0.350,<0.0.351)
Requires-Dist: markdown-it-py (>=3.0.0,<4.0.0)
Requires-Dist: mdurl (>=0.1.2,<0.2.0)
Requires-Dist: openai (>=1.3.9,<2.0.0)
Requires-Dist: pydantic (>=2.5.2,<3.0.0)
Requires-Dist: pydantic-core (>=2.14.5,<3.0.0)
Requires-Dist: pygments (>=2.17.2,<3.0.0)
Requires-Dist: pyperclip (>=1.8.2,<2.0.0)
Requires-Dist: rich (>=13.7.0,<14.0.0)
Requires-Dist: sniffio (>=1.3.0,<2.0.0)
Requires-Dist: toml (>=0.10.2,<0.11.0)
Requires-Dist: tqdm (>=4.66.1,<5.0.0)
Requires-Dist: typing-extensions (>=4.9.0,<5.0.0)
